{"grobianabi": {"message_count": 0, "join_date": "04.02.2026", "xp": 0, "rank": "beginner", "next_rank": "member", "xp_for_next_rank": 500}, "sanchous23": {"message_count": 0, "join_date": "05.02.2026", "xp": 0, "rank": "beginner", "next_rank": "member", "xp_for_next_rank": 500}, "mrpurplemonster": {"message_count": 0, "join_date": "28.01.2026", "xp": 0, "rank": "beginner", "next_rank": "member", "xp_for_next_rank": 500}, "fogtei": {"message_count": 0, "join_date": "03.02.2026", "xp": 0, "rank": "beginner", "next_rank": "member", "xp_for_next_rank": 500}, "fjshyyy": {"message_count": 0, "join_date": "29.01.2026", "xp": 0, "rank": "beginner", "next_rank": "member", "xp_for_next_rank": 500}, "vhxpnoticshi": {"message_count": 0, "join_date": "03.02.2026", "xp": 0, "rank": "beginner", "next_rank": "member", "xp_for_next_rank": 500}, "divad3527": {"message_count": 1, "join_date": "04.02.2026", "xp": 5, "rank": "beginner", "next_rank": "member", "xp_for_next_rank": 500}, "franzoskek": {"message_count": 0, "join_date": "28.01.2026", "xp": 0, "rank": "beginner", "next_rank": "member", "xp_for_next_rank": 500}, "blob3558": {"message_count": 0, "join_date": "28.01.2026", "xp": 0, "rank": "beginner", "next_rank": "member", "xp_for_next_rank": 500}, "leafarroka1.0": {"message_count": 147, "join_date": "28.01.2026", "xp": 8005, "rank": "trial dev", "next_rank": "dev", "xp_for_next_rank": 4500}, "kannnno_": {"message_count": 0, "join_date": "28.01.2026", "xp": 0, "rank": "beginner", "next_rank": "member", "xp_for_next_rank": 500}, "hiroshi1555.": {"message_count": 0, "join_date": "04.02.2026", "xp": 0, "rank": "beginner", "next_rank": "member", "xp_for_next_rank": 500}, "leafarroka2.0": {"message_count": 2, "join_date": "28.01.2026", "xp": 10, "rank": "dev", "next_rank": "mini mod", "xp_for_next_rank": "through votes of users with the rank member or higher"}}